LT22004UNO/Ecuaciones_lineales.py
LT22004UNO/Ecuaciones_no_lineales.py
LT22004UNO/__init__.py
LT22004UNO/utils.py
lt22004uno-0.1.2.dist-info/licenses/LICENSE
tests/__init__.py
tests/test_lineal.py
tests/test_nolinear.py
lt22004uno-0.1.2.dist-info/METADATA
lt22004uno-0.1.2.dist-info/WHEEL
lt22004uno-0.1.2.dist-info/top_level.txt
lt22004uno-0.1.2.dist-info/RECORD
